README.md
setup.py
stagesep2/__init__.py
stagesep2/config.py
stagesep2/executor.py
stagesep2/loader.py
stagesep2/logger.py
stagesep2/painter.py
stagesep2/reporter.py
stagesep2/utils.py
stagesep2.egg-info/PKG-INFO
stagesep2.egg-info/SOURCES.txt
stagesep2.egg-info/dependency_links.txt
stagesep2.egg-info/requires.txt
stagesep2.egg-info/top_level.txt
stagesep2/analyser/__init__.py
stagesep2/analyser/base.py
stagesep2/analyser/match_template.py
stagesep2/analyser/ocr.py
stagesep2/analyser/trend.py