Metadata-Version: 1.2
Name: stagesep2
Version: 0.2.6
Summary: Analyse, and convert video into useful data.
Home-page: https://github.com/williamfzc/stagesep2
Author: williamfzc
Author-email: fengzc@vip.qq.com
License: MIT
Platform: UNKNOWN
Classifier: License :: OSI Approved :: MIT License
Classifier: Programming Language :: Python
Classifier: Programming Language :: Python :: 3
Classifier: Programming Language :: Python :: 3.6
Classifier: Programming Language :: Python :: 3.7
Requires-Python: >=3.6
